CONTRIBUTORS.txt
LICENSE.txt
MANIFEST.in
README.rst
setup.py
dist/emencia.recipe.patch-0.1/CONTRIBUTORS.txt
dist/emencia.recipe.patch-0.1/LICENSE.txt
dist/emencia.recipe.patch-0.1/emencia.recipe.patch.egg-info/SOURCES.txt
dist/emencia.recipe.patch-0.1/emencia.recipe.patch.egg-info/dependency_links.txt
dist/emencia.recipe.patch-0.1/emencia.recipe.patch.egg-info/entry_points.txt
dist/emencia.recipe.patch-0.1/emencia.recipe.patch.egg-info/namespace_packages.txt
dist/emencia.recipe.patch-0.1/emencia.recipe.patch.egg-info/requires.txt
dist/emencia.recipe.patch-0.1/emencia.recipe.patch.egg-info/top_level.txt
emencia/__init__.py
emencia.recipe.patch.egg-info/PKG-INFO
emencia.recipe.patch.egg-info/SOURCES.txt
emencia.recipe.patch.egg-info/dependency_links.txt
emencia.recipe.patch.egg-info/entry_points.txt
emencia.recipe.patch.egg-info/namespace_packages.txt
emencia.recipe.patch.egg-info/requires.txt
emencia.recipe.patch.egg-info/top_level.txt
emencia.recipe.patch.egg-info/zip-safe
emencia/recipe/__init__.py
emencia/recipe/patch/__init__.py
emencia/recipe/patch/tests/__init__.py
emencia/recipe/patch/tests/test_docs.py