Metadata-Version: 1.1
Name: emencia.recipe.patch
Version: 0.1
Summary: recipe for patching eggs
Home-page: http://github.com/emencia/emencia.recipe.patch
Author: J. David Ibanez
Author-email: jdavid@emencia.com
License: GPL
Keywords: buildout recipe patch
Platform: UNKNOWN
Classifier: Framework :: Buildout
Classifier: Intended Audience :: Developers
Classifier: Topic :: Software Development :: Build Tools
Classifier: Topic :: Software Development :: Libraries :: Python Modules
Classifier: License :: OSI Approved :: GNU General Public License (GPL)
